<?xml version="1.0" encoding="utf-8"?>
<!-- Created by ModBuddy on 6/24/2014 12:46:57 PM -->
<GameData>
	<Language_en_US>
		
		<!-- Top Panel -->
		<Row Tag="TXT_KEY_TP_UNHAPPINESS_SCIENCE">
			<Text>{1_Num} from [ICON_RESEARCH] Illiteracy.</Text>
		</Row>
		<Row Tag="TXT_KEY_TP_UNHAPPINESS_CULTURE">
			<Text>{1_Num} from [ICON_CULTURE] Boredom.</Text>
		</Row>
		<Row Tag="TXT_KEY_TP_UNHAPPINESS_DEFENSE">
			<Text>{1_Num} from [ICON_STRENGTH] Crime.</Text>
		</Row>
		<Row Tag="TXT_KEY_TP_UNHAPPINESS_GOLD">
			<Text>{1_Num} from [ICON_GOLD] Poverty.</Text>
		</Row>
		<Row Tag="TXT_KEY_TP_UNHAPPINESS_CONNECTION">
			<Text>{1_Num} from [ICON_BLOCKADED] Isolation.</Text>
		</Row>
		<Row Tag="TXT_KEY_TP_UNHAPPINESS_PILLAGED">
			<Text>{1_Num} from [ICON_RAZING] Pillaged Tiles.</Text>
		</Row>
		<Row Tag="TXT_KEY_TP_UNHAPPINESS_STARVING">
			<Text>{1_Num} from [ICON_FOOD] Famine.</Text>
		</Row>
		<Row Tag="TXT_KEY_TP_UNHAPPINESS_MINORITY">
			<Text>{1_Num} from [ICON_RELIGION] Religious Divisions.</Text>
		</Row>
		
		<!-- Economic Overview -->
		<Row Tag="TXT_KEY_EO_CITY_IS_NOT_OCCUPIED">
			<Text>Sources of [ICON_HAPPINESS_3] [COLOR_NEGATIVE_TEXT]Unhappiness[ENDCOLOR]:</Text>
		</Row>
		<Row Tag="TXT_KEY_EO_CITY_LOCAL_UNHAPPINESS">
			<Text>Local [ICON_HAPPINESS_3] Unhappiness: [COLOR_NEGATIVE_TEXT]{1_NUM}[ENDCOLOR]</Text>
		</Row>

		<Row Tag="TXT_KEY_PUPPET_UNHAPPINESS_MOD">
			<Text>[ICON_BULLET] [ICON_PUPPET] Puppet Needs: {1_Num}%[NEWLINE]</Text>
		</Row>
		<Row Tag="TXT_KEY_CAPITAL_UNHAPPINESS_MOD">
			<Text>[ICON_BULLET] [ICON_CAPITAL] Capital Needs: +{1_Num}%[NEWLINE]</Text>
		</Row>
		<Row Tag="TXT_KEY_CITYCOUNT_UNHAPPINESS">
			<Text>[ICON_BULLET] [COLOR_NEGATIVE_TEXT]{1_Num}[ENDCOLOR] from Number of Cities.</Text>
		</Row>
		<Row Tag="TXT_KEY_SCIENCE_UNHAPPINESS">
			<Text>[ICON_BULLET] [COLOR_NEGATIVE_TEXT]{1_Num}[ENDCOLOR] from Illiteracy ([ICON_RESEARCH]). [NEWLINE]          Produces: [COLOR_POSITIVE_TEXT]{2_Num}[ENDCOLOR] [ICON_RESEARCH] per [ICON_CITIZEN][NEWLINE]          Needs: [COLOR_POSITIVE_TEXT]{3_Num}[ENDCOLOR] [ICON_RESEARCH] per [ICON_CITIZEN][NEWLINE]          Deficit: [COLOR_POSITIVE_TEXT]{4_Num}[ENDCOLOR] [ICON_RESEARCH]</Text>
		</Row>
		<Row Tag="TXT_KEY_CULTURE_UNHAPPINESS">
			<Text>[ICON_BULLET] [COLOR_NEGATIVE_TEXT]{1_Num}[ENDCOLOR] from Boredom ([ICON_CULTURE]). [NEWLINE]          Produces: [COLOR_POSITIVE_TEXT]{2_Num}[ENDCOLOR] [ICON_CULTURE] per [ICON_CITIZEN][NEWLINE]          Needs: [COLOR_POSITIVE_TEXT]{3_Num}[ENDCOLOR] [ICON_CULTURE] per [ICON_CITIZEN][NEWLINE]          Deficit: [COLOR_POSITIVE_TEXT]{4_Num}[ENDCOLOR] [ICON_CULTURE]</Text>
		</Row>
		<Row Tag="TXT_KEY_DEFENSE_UNHAPPINESS">
			<Text>[ICON_BULLET] [COLOR_NEGATIVE_TEXT]{1_Num}[ENDCOLOR] from Crime ([ICON_STRENGTH]). [NEWLINE]          Produces: [COLOR_POSITIVE_TEXT]{2_Num}[ENDCOLOR] [ICON_STRENGTH] per [ICON_CITIZEN][NEWLINE]          Needs: [COLOR_POSITIVE_TEXT]{3_Num}[ENDCOLOR] [ICON_STRENGTH] per [ICON_CITIZEN][NEWLINE]          Deficit: [COLOR_POSITIVE_TEXT]{4_Num}[ENDCOLOR] [ICON_STRENGTH]</Text>
		</Row>
		<Row Tag="TXT_KEY_GOLD_UNHAPPINESS">
			<Text>[ICON_BULLET] [COLOR_NEGATIVE_TEXT]{1_Num}[ENDCOLOR] from Poverty ([ICON_GOLD]). [NEWLINE]          Produces: [COLOR_POSITIVE_TEXT]{2_Num}[ENDCOLOR] [ICON_GOLD] per [ICON_CITIZEN][NEWLINE]          Needs: [COLOR_POSITIVE_TEXT]{3_Num}[ENDCOLOR] [ICON_GOLD] per [ICON_CITIZEN][NEWLINE]          Deficit: [COLOR_POSITIVE_TEXT]{4_Num}[ENDCOLOR] [ICON_GOLD]</Text>
		</Row>
		<Row Tag="TXT_KEY_CONNECTION_UNHAPPINESS">
			<Text>[ICON_BULLET] [COLOR_NEGATIVE_TEXT]{1_Num}[ENDCOLOR] from Isolation ([ICON_BLOCKADED] Blockaded, lacks [ICON_CONNECTED] Connection, or needs [ICON_INTERNATIONAL_TRADE] Trade Route with [ICON_CAPITAL] Capital).</Text>
		</Row>
		<Row Tag="TXT_KEY_PILLAGED_UNHAPPINESS">
			<Text>[ICON_BULLET] [COLOR_NEGATIVE_TEXT]{1_Num}[ENDCOLOR] from [ICON_RAZING] Pillaged Tiles.</Text>
		</Row>
		<Row Tag="TXT_KEY_STARVING_UNHAPPINESS">
			<Text>[ICON_BULLET] [COLOR_NEGATIVE_TEXT]{1_Num}[ENDCOLOR] from Famine (Needs [ICON_FOOD]).</Text>
		</Row>
		<Row Tag="TXT_KEY_MINORITY_UNHAPPINESS">
			<Text>[ICON_BULLET] [COLOR_NEGATIVE_TEXT]{1_Num}[ENDCOLOR] from Religious Divisions (Needs Majority Religion [ICON_RELIGION] Followers).</Text>
		</Row>
		<Row Tag="TXT_KEY_RESISTANCE_UNHAPPINESS">
			<Text>[ICON_BULLET] [COLOR_NEGATIVE_TEXT]{1_Num}[ENDCOLOR] from [ICON_RESISTANCE] Resistance.</Text>
		</Row>
		<Row Tag="TXT_KEY_OCCUPATION_UNHAPPINESS">
			<Text>[ICON_BULLET] [COLOR_NEGATIVE_TEXT]{1_Num}[ENDCOLOR] from [ICON_OCCUPIED] Occupation.</Text>
		</Row>

		<!-- Surplus Threshold -->
		<Row Tag="TXT_KEY_CULTURE_UNHAPPINESS_SURPLUS">
			<Text>[ICON_BULLET] [COLOR_POSITIVE_TEXT]{1_Num}[ENDCOLOR] above [ICON_CULTURE] Need.</Text>
		</Row>
		<Row Tag="TXT_KEY_SCIENCE_UNHAPPINESS_SURPLUS">
			<Text>[ICON_BULLET] [COLOR_POSITIVE_TEXT]{1_Num}[ENDCOLOR] above [ICON_RESEARCH] Need.</Text>
		</Row>
		<Row Tag="TXT_KEY_DEFENSE_UNHAPPINESS_SURPLUS">
			<Text>[ICON_BULLET] [COLOR_POSITIVE_TEXT]{1_Num}[ENDCOLOR] above [ICON_STRENGTH] Need.</Text>
		</Row>
		<Row Tag="TXT_KEY_GOLD_UNHAPPINESS_SURPLUS">
			<Text>[ICON_BULLET] [COLOR_POSITIVE_TEXT]{1_Num}[ENDCOLOR] above [ICON_GOLD] Need.</Text>
		</Row>

		<Row Tag="TXT_KEY_EO_CITY_OCCUPATION">
			<Text>[COLOR_NEGATIVE_TEXT]({1_Num})[ENDCOLOR] [ICON_CITIZEN]: "Fight the [ICON_OCCUPIED] Oppressors!"</Text>
		</Row>
		<Row Tag="TXT_KEY_EO_CITY_RESISTANCE">
			<Text>[COLOR_NEGATIVE_TEXT]({1_Num})[ENDCOLOR] [ICON_CITIZEN]: "[ICON_RESISTANCE] Viva la Revolucion!"</Text>
		</Row>
		<Row Tag="TXT_KEY_EO_CITY_UNEDUCATED">
			<Text>[COLOR_NEGATIVE_TEXT]({1_Num})[ENDCOLOR] [ICON_CITIZEN]: "We are [ICON_RESEARCH] illiterate!"</Text>
		</Row>
		<Row Tag="TXT_KEY_EO_CITY_UNDEFENDED">
			<Text>[COLOR_NEGATIVE_TEXT]({1_Num})[ENDCOLOR] [ICON_CITIZEN]: "This city is [ICON_STRENGTH] dangerous!"</Text>
		</Row>
		<Row Tag="TXT_KEY_EO_CITY_POOR">
			<Text>[COLOR_NEGATIVE_TEXT]({1_Num})[ENDCOLOR] [ICON_CITIZEN]: "We are [ICON_GOLD] impoverished!"</Text>
		</Row>
		<Row Tag="TXT_KEY_EO_CITY_UNCULTURED">
			<Text>[COLOR_NEGATIVE_TEXT]({1_Num})[ENDCOLOR] [ICON_CITIZEN]: "Our city is [ICON_CULTURE] boring!"</Text>
		</Row>
		<Row Tag="TXT_KEY_EO_CITY_UNCONNECTED">
			<Text>[COLOR_NEGATIVE_TEXT]({1_Num})[ENDCOLOR] [ICON_CITIZEN]: "We are [ICON_BLOCKADED] disconnected!"</Text>
		</Row>
		<Row Tag="TXT_KEY_EO_CITY_PILLAGED">
			<Text>[COLOR_NEGATIVE_TEXT]({1_Num})[ENDCOLOR] [ICON_CITIZEN]: "Our lands are [ICON_RAZING] burning!"</Text>
		</Row>
		<Row Tag="TXT_KEY_EO_CITY_STARVING">
			<Text>[COLOR_NEGATIVE_TEXT]({1_Num})[ENDCOLOR] [ICON_CITIZEN]: "There is not enough [ICON_FOOD] food!"</Text>
		</Row>
		<Row Tag="TXT_KEY_EO_CITY_RELIGION">
			<Text>[COLOR_NEGATIVE_TEXT]({1_Num})[ENDCOLOR] [ICON_CITIZEN]: "We want more {2_ReligionIcon} followers!"</Text>
		</Row>
		
		<!-- Luxury Tooltip -->
		<Row Tag="TXT_KEY_TP_HAPPINESS_THRESHOLD_VALUE">
			<Text>Based on your current [ICON_CITIZEN] Population ([COLOR_POSITIVE_TEXT]{2_Num}[ENDCOLOR]), acquiring a new Luxury Resource will increase your [ICON_HAPPINESS_1] Happiness by [COLOR_POSITIVE_TEXT]{3_Num}[ENDCOLOR]. To increase the [ICON_HAPPINESS_1] Happiness you gain from all owned Luxuries, raise your [ICON_CITIZEN] Population in [ICON_PUPPET] non-Puppet Cities to [COLOR_POSITIVE_TEXT]{1_Num}[ENDCOLOR].</Text>
		</Row>
		
		<Row Tag="TXT_KEY_EO_CITY_CONNECTED">
			<Text>[COLOR_POSITIVE_TEXT]Connected[ENDCOLOR]</Text>
		</Row>
		
		<!-- LUA for Buildings -->
		<Row Tag="TXT_KEY_BUILDING_POVERTY_AVERAGE_MODIFIER">
			<Text>[ICON_GOLD] Gold Need Modifier: {1_num}%</Text>
		</Row>

		<Row Tag="TXT_KEY_BUILDING_DEFENSE_AVERAGE_MODIFIER">
			<Text>[ICON_STRENGTH] Defense Need Modifier: {1_num}%</Text>
		</Row>

		<Row Tag="TXT_KEY_BUILDING_CULTURE_AVERAGE_MODIFIER">
			<Text>[ICON_CULTURE] Culture Need Modifier: {1_num}%</Text>
		</Row>

		<Row Tag="TXT_KEY_BUILDING_SCIENCE_AVERAGE_MODIFIER">
			<Text>[ICON_RESEARCH] Science Need Modifier: {1_num}%</Text>
		</Row>

		<Row Tag="TXT_KEY_BUILDING_MINORITY_AVERAGE_MODIFIER">
			<Text>[ICON_RELIGION] Religious Need Modifier: {1_num}%</Text>
		</Row>

		<Row Tag="TXT_KEY_BUILDING_POVERTY_GLOBAL_AVERAGE_MODIFIER">
			<Text>[ICON_GOLD] Gold Need Modifier in all Cities: {1_num}%</Text>
		</Row>

		<Row Tag="TXT_KEY_BUILDING_DEFENSE_GLOBAL_AVERAGE_MODIFIER">
			<Text>[ICON_STRENGTH] Defense Need Modifier in all Cities: {1_num}%</Text>
		</Row>

		<Row Tag="TXT_KEY_BUILDING_CULTURE_GLOBAL_AVERAGE_MODIFIER">
			<Text>[ICON_CULTURE] Culture Need Modifier in all Cities: {1_num}%</Text>
		</Row>

		<Row Tag="TXT_KEY_BUILDING_SCIENCE_GLOBAL_AVERAGE_MODIFIER">
			<Text>[ICON_RESEARCH] Science Need Modifier in all Cities: {1_num}%</Text>
		</Row>

		<Row Tag="TXT_KEY_BUILDING_MINORITY_GLOBAL_AVERAGE_MODIFIER">
			<Text>[ICON_RELIGION] Religious Need Modifier in all Cities: {1_num}%</Text>
		</Row>
		
		<!-- LUA Threshold Mods for Buildings -->
		<Row Tag="TXT_KEY_BUILDING_POVERTY_NEW_THRESHOLD">
			<Text>[ICON_BULLET] New Need: {1_num} [ICON_GOLD] per [ICON_CITIZEN][NEWLINE][ICON_BULLET] Current: {2_Num} [ICON_GOLD] per [ICON_CITIZEN]</Text>
		</Row>
		<Row Tag="TXT_KEY_BUILDING_ILLITERACY_NEW_THRESHOLD">
			<Text>[ICON_BULLET] New Need: {1_num} [ICON_RESEARCH] per [ICON_CITIZEN][NEWLINE][ICON_BULLET] Current: {2_Num} [ICON_RESEARCH] per [ICON_CITIZEN]</Text>
		</Row>
		<Row Tag="TXT_KEY_BUILDING_DEFENSE_NEW_THRESHOLD">
			<Text>[ICON_BULLET] New Need: {1_num} [ICON_STRENGTH] per [ICON_CITIZEN][NEWLINE][ICON_BULLET] Current: {2_Num} [ICON_STRENGTH] per [ICON_CITIZEN]</Text>
		</Row>
		<Row Tag="TXT_KEY_BUILDING_CULTURE_NEW_THRESHOLD">
			<Text>[ICON_BULLET] New Need: {1_num} [ICON_CULTURE] per [ICON_CITIZEN][NEWLINE][ICON_BULLET] Current: {2_Num} [ICON_CULTURE] per [ICON_CITIZEN]</Text>
		</Row>

		<!-- More LUA! -->
		<Row Tag="TXT_KEY_NET_HAPPINESS_TEXT">
			<Text>[COLOR_CYAN]{1_num}[ENDCOLOR]</Text>
		</Row>
		<Row Tag="TXT_KEY_CITYVIEW_HAPPINESS_TEXT">
			<Text>[COLOR_CYAN]Happiness[ENDCOLOR]</Text>
		</Row>
		<Row Tag="TXT_KEY_EO_CITY_LOCAL_HAPPINESS_EXPLANATION">
			<Text>[NEWLINE](Only includes local [ICON_HAPPINESS_1] Happiness provided by buildings, policies and beliefs specific to this City.)</Text>
		</Row>
		<Row Tag="TXT_KEY_EO_CITY_LOCAL_UNHAPPINESS_EXPLANATION">
			<Text>[NEWLINE](These 'Needs' are global averages of yields based on the number of [ICON_CITIZEN] Citizens in the City, as well as temporary situations, such as starvation or blockades. Global averages increase as the game progresses, and yields per citizen decrease as a city grows. The bigger the divide between your city's yields and the global average, the higher your city's unhappiness!)</Text>
		</Row>
		<Row Tag="TXT_KEY_EO_CITY_LOCAL_HAPPINESS">
			<Text>Local [ICON_HAPPINESS_1] Happiness: [COLOR_POSITIVE_TEXT]{1_NUM}[ENDCOLOR]</Text>
		</Row>
		<Row Tag="TXT_KEY_EO_CITY_GLOBAL_AVERAGE_MODS">
			<Text>[COLOR_POSITIVE_TEXT]Global Average (Need) Modifiers:[ENDCOLOR]</Text>
		</Row>
		<Row Tag="TXT_KEY_GLOBAL_AVERAGE_MOD_GOLD">
			<Text>[ICON_BULLET] [ICON_GOLD] Gold Need: {1_Num}%</Text>
		</Row>
		<Row Tag="TXT_KEY_GLOBAL_AVERAGE_MOD_SCIENCE">
			<Text>[ICON_BULLET] [ICON_RESEARCH] Science Need: {1_Num}%</Text>
		</Row>
		<Row Tag="TXT_KEY_GLOBAL_AVERAGE_MOD_DEFENSE">
			<Text>[ICON_BULLET] [ICON_STRENGTH] Defense Need: {1_Num}%</Text>
		</Row>
		<Row Tag="TXT_KEY_GLOBAL_AVERAGE_MOD_CULTURE">
			<Text>[ICON_BULLET] [ICON_CULTURE] Culture Need: {1_Num}%</Text>
		</Row>

		<Row Tag="TXT_KEY_GLOBAL_AVERAGE_MOD_GOLD_POSITIVE">
			<Text>[ICON_BULLET] [ICON_GOLD] Gold Need: +{1_Num}%</Text>
		</Row>
		<Row Tag="TXT_KEY_GLOBAL_AVERAGE_MOD_SCIENCE_POSITIVE">
			<Text>[ICON_BULLET] [ICON_RESEARCH] Science Need: +{1_Num}%</Text>
		</Row>
		<Row Tag="TXT_KEY_GLOBAL_AVERAGE_MOD_DEFENSE_POSITIVE">
			<Text>[ICON_BULLET] [ICON_STRENGTH] Defense Need: +{1_Num}%</Text>
		</Row>
		<Row Tag="TXT_KEY_GLOBAL_AVERAGE_MOD_CULTURE_POSITIVE">
			<Text>[ICON_BULLET] [ICON_CULTURE] Culture Need: +{1_Num}%</Text>
		</Row>

		<Row Tag="TXT_KEY_EO_CITY_GLOBAL_AVERAGE_MODS_EXPLANATION">
			<Text>[NEWLINE](These modifiers are based on a number of factors, such as the size of the City, Technologies researched, Policies chosen, Buildings constructed and/or Civilization traits. Special traits, such as being the [ICON_CAPITAL] Capital or a [ICON_PUPPET] Puppet, are highlighted. Positive modifiers raise the global average for this city, whereas negative modifiers reduce it.)</Text>
		</Row>

	</Language_en_US>
</GameData>